Metadata-Version: 1.0
Name: StackMan
Version: 0.1
Summary: Simple stack manager for developing websites for Python 3
Home-page: http://github.com/ColtonProvias/stackman
Author: Colton J. Provias
Author-email: cj@coltonprovias.com
License: UNKNOWN
Platform: UNKNOWN
